Metadata-Version: 2.1
Name: pyzerolog
Version: 0.0.2
Summary: Package that makes typed logging convinient.
Author: Kraysent
License: MIT License
License-File: LICENSE
